<?xml version="1.0" encoding="utf-8" ?><dwsync><file name="site-breadcrumbs.php" server="ftp.achcreative.info//public_html/dev-vcmpublications/" local="3697806509" remote="321349495439558124" Dst="-1" /><file name="featured-content.php" server="ftp.achcreative.info//public_html/dev-vcmpublications/" local="3697806509" remote="321349495439558184" Dst="-1" /><file name="site-logo.php" server="ftp.achcreative.info//public_html/dev-vcmpublications/" local="3697806509" remote="321349495439558184" Dst="-1" /><file name="infinite-scroll.php" server="ftp.achcreative.info//public_html/dev-vcmpublications/" local="3697806509" remote="321349495439558184" Dst="-1" /><file name="responsive-videos.php" server="ftp.achcreative.info//public_html/dev-vcmpublications/" local="3697806509" remote="321349495439558184" Dst="-1" /><file name="random-redirect.php" server="ftp.achcreative.info//public_html/dev-vcmpublications/" local="3697806509" remote="321349495439558184" Dst="-1" /><file name="content-options.php" server="ftp.achcreative.info//public_html/dev-vcmpublications/" local="3697806509" remote="321349495439558184" Dst="-1" /><file name="social-menu.php" server="ftp.achcreative.info//public_html/dev-vcmpublications/" local="3697806509" remote="321349495439558184" Dst="-1" /><file name="social-links.php" server="ftp.achcreative.info//public_html/dev-vcmpublications/" local="3697806509" remote="321349495439558184" Dst="-1" /><file name="devicepx.php" server="ftp.achcreative.info//public_html/dev-vcmpublications/" local="3697806509" remote="321349495439558184" Dst="-1" /></dwsync>