<?xml version="1.0" encoding="utf-8" ?><dwsync><file name="folder.js" server="ftpupload.net//htdocs/" local="3698238029" remote="321155981393742568" Dst="-1" /><file name="notice.js" server="ftpupload.net//htdocs/" local="3698238029" remote="321155981393742568" Dst="-1" /><file name="review.js" server="ftpupload.net//htdocs/" local="3698238029" remote="321155981393742568" Dst="-1" /><file name="woo.js" server="ftpupload.net//htdocs/" local="3698238029" remote="321155981393742568" Dst="-1" /><file name="check-payment.js" server="ftpupload.net//htdocs/" local="3698238029" remote="321155981393742568" Dst="-1" /><file name="notes.js" server="ftpupload.net//htdocs/" local="3698238029" remote="321155981393742568" Dst="-1" /><file name="radio-selected.js" server="ftpupload.net//htdocs/" local="3698238029" remote="321155981393742568" Dst="-1" /><file name="truck.js" server="ftpupload.net//htdocs/" local="3698238029" remote="321155981393742568" Dst="-1" /><file name="thumb-up.js" server="ftpupload.net//htdocs/" local="3698238029" remote="321155981393742568" Dst="-1" /><file name="bank.js" server="ftpupload.net//htdocs/" local="3698238029" remote="321155981393742568" Dst="-1" /><file name="star.js" server="ftpupload.net//htdocs/" local="3698238029" remote="321155981393742568" Dst="-1" /><file name="cart.js" server="ftpupload.net//htdocs/" local="3698238029" remote="321155981393742568" Dst="-1" /><file name="box.js" server="ftpupload.net//htdocs/" local="3698238029" remote="321155981393742568" Dst="-1" /><file name="server.js" server="ftpupload.net//htdocs/" local="3698238029" remote="321155981393742568" Dst="-1" /><file name="grid.js" server="ftpupload.net//htdocs/" local="3698238029" remote="321155981393742568" Dst="-1" /><file name="folder-starred.js" server="ftpupload.net//htdocs/" local="3698238029" remote="321155981393742568" Dst="-1" /><file name="tags.js" server="ftpupload.net//htdocs/" local="3698238029" remote="321155981393742568" Dst="-1" /><file name="bill.js" server="ftpupload.net//htdocs/" local="3698238029" remote="321155981393742568" Dst="-1" /><file name="toggle.js" server="ftpupload.net//htdocs/" local="3698238029" remote="321155981393742568" Dst="-1" /><file name="arrow-back.js" server="ftpupload.net//htdocs/" local="3698238029" remote="321155981393742568" Dst="-1" /><file name="stonks.js" server="ftpupload.net//htdocs/" local="3698238029" remote="321155981393742568" Dst="-1" /><file name="radio-unselected.js" server="ftpupload.net//htdocs/" local="3698238029" remote="321155981393742568" Dst="-1" /><file name="remove-cart.js" server="ftpupload.net//htdocs/" local="3698238029" remote="321155981393742568" Dst="-1" /><file name="list.js" server="ftpupload.net//htdocs/" local="3698238029" remote="321155981393742568" Dst="-1" /><file name="comment.js" server="ftpupload.net//htdocs/" local="3698238029" remote="321155981393742568" Dst="-1" /><file name="external.js" server="ftpupload.net//htdocs/" local="3698238029" remote="321155981393742568" Dst="-1" /><file name="chevron-up.js" server="ftpupload.net//htdocs/" local="3698238029" remote="321155981393742568" Dst="-1" /><file name="exclamation.js" server="ftpupload.net//htdocs/" local="3698238029" remote="321155981393742568" Dst="-1" /><file name="chevron-down.js" server="ftpupload.net//htdocs/" local="3698238029" remote="321155981393742568" Dst="-1" /><file name="done.js" server="ftpupload.net//htdocs/" local="3698238029" remote="321155981393742568" Dst="-1" /><file name="discussion.js" server="ftpupload.net//htdocs/" local="3698238029" remote="321155981393742568" Dst="-1" /><file name="tag.js" server="ftpupload.net//htdocs/" local="3698238029" remote="321155981393742568" Dst="-1" /><file name="image.js" server="ftpupload.net//htdocs/" local="3698238029" remote="321155981393742568" Dst="-1" /><file name="atom.js" server="ftpupload.net//htdocs/" local="3698238029" remote="321155981393742568" Dst="-1" /><file name="restore.js" server="ftpupload.net//htdocs/" local="3698238029" remote="321155981393742568" Dst="-1" /><file name="reader.js" server="ftpupload.net//htdocs/" local="3698238029" remote="321155981393742568" Dst="-1" /><file name="heading.js" server="ftpupload.net//htdocs/" local="3698238029" remote="321155981393742568" Dst="-1" /><file name="more.js" server="ftpupload.net//htdocs/" local="3698238029" remote="321155981393742568" Dst="-1" /><file name="bookmark.js" server="ftpupload.net//htdocs/" local="3698238029" remote="321155981393742568" Dst="-1" /><file name="widgets.js" server="ftpupload.net//htdocs/" local="3698238029" remote="321155981393742568" Dst="-1" /><file name="card.js" server="ftpupload.net//htdocs/" local="3698238029" remote="321155981393742568" Dst="-1" /><file name="search.js" server="ftpupload.net//htdocs/" local="3698238029" remote="321155981393742568" Dst="-1" /><file name="barcode.js" server="ftpupload.net//htdocs/" local="3698238029" remote="321155981393742568" Dst="-1" /><file name="arrow-down-alt2.js" server="ftpupload.net//htdocs/" local="3698238029" remote="321155981393742568" Dst="-1" /><file name="no-alt.js" server="ftpupload.net//htdocs/" local="3698238029" remote="321155981393742568" Dst="-1" /></dwsync>